qiskit_connector/__ini__.txt
qiskit_connector/__init__.py
qiskit_connector/qcon_lib.py
qiskit_connector/media/QConnV2.ico
qiskit_connector/media/canary-2017-effects.png
qiskit_connector/media/canary-2017-removebg.png
qiskit_connector/media/canary-2017.png
qiskit_connector/media/condor-2023-effects.png
qiskit_connector/media/condor-2023-removebg.png
qiskit_connector/media/condor-2023.png
qiskit_connector/media/eagle-2021-effects.png
qiskit_connector/media/eagle-2021-removebg.png
qiskit_connector/media/eagle-2021.png
qiskit_connector/media/egret-2023-effects.png
qiskit_connector/media/egret-2023-removebg.png
qiskit_connector/media/egret-2023.png
qiskit_connector/media/falcon-2019-effects.png
qiskit_connector/media/falcon-2019-removebg.png
qiskit_connector/media/falcon-2019.png
qiskit_connector/media/flamingo-2025-effects.png
qiskit_connector/media/flamingo-2025-removebg.png
qiskit_connector/media/flamingo-2025.png
qiskit_connector/media/heron-2023-effects.png
qiskit_connector/media/heron-2023-removebg.png
qiskit_connector/media/heron-2023.png
qiskit_connector/media/hummingbird-2019-effects.png
qiskit_connector/media/hummingbird-2019-removebg.png
qiskit_connector/media/hummingbird-2019.png
qiskit_connector/media/osprey-2022-effects.png
qiskit_connector/media/osprey-2022-removebg.png
qiskit_connector/media/osprey-2022.png
qiskit_connector/media/q1.png
qiskit_connector/media/sample-output-0.png
qiskit_connector/media/sample-output-00.png
qiskit_connector/store_media/canary-2017-effects.png
qiskit_connector-2.4.6.dist-info/licenses/LICENSE
qiskit_connector-2.4.6.dist-info/METADATA
qiskit_connector-2.4.6.dist-info/WHEEL
qiskit_connector-2.4.6.dist-info/top_level.txt
qiskit_connector-2.4.6.dist-info/RECORD
