Metadata-Version: 2.4
Name: qiskit-connector
Version: 2.4.6
Summary: Quantum Computing Qiskit Connector For Quantum Backend Use In Realtime
Home-page: https://github.com/schijioke-uche/qiskit-connector
Author: Dr. Jeffrey Chijioke-Uche
Author-email: "Dr. Jeffrey Chijioke-Uche (Software Owner)" <sj@chijioke-uche.com>
Maintainer-email: "Dr. Jeffrey Chijioke-Uche" <sj@chijioke-uche.com>
License:          Copyright ©2025 Dr. Jeffrey Chijioke-Uche - All Rights Reserved
Project-URL: Homepage, https://github.com/schijioke-uche/pypi-qiskit-connector
Project-URL: Source, https://github.com/schijioke-uche/pypi-qiskit-connector
Project-URL: Tracker, https://github.com/schijioke-uche/pypi-qiskit-connector/issues
Project-URL: Software Publisher, https://doi.org/10.5281/zenodo.15304310
Keywords: qiskit connector,quantum connection,quantum computing,ibm quantum,qiskit,quantum runtimeservice,quantum automated backend connectors,qpu resources,qubits processing unit,quantum programming language,quantum circuit,quantum open plan,quantum premier plan,quantum standard plan,quantum dedicated plan,quantum paid plan,quantum workloads,physical quantum computer,quantum algorithms,qiskit integration libraries,qiskit connector interface,python wrapper for Qiskit,production-ready Qiskit tool
Classifier: Environment :: Console
Classifier: Development Status :: 5 - Production/Stable
Classifier: Intended Audience :: Developers
Classifier: Intended Audience :: Science/Research
Classifier: Intended Audience :: Information Technology
Classifier: Intended Audience :: System Administrators
Classifier: Topic :: Scientific/Engineering
Classifier: Topic :: Scientific/Engineering :: Quantum Computing
Classifier: Topic :: Scientific/Engineering :: Artificial Intelligence
Classifier: Topic :: Scientific/Engineering :: Information Analysis
Classifier: Topic :: Scientific/Engineering :: Physics
Classifier: Topic :: Scientific/Engineering :: Mathematics
Classifier: Topic :: Scientific/Engineering :: Chemistry
Classifier: Topic :: Scientific/Engineering :: Astronomy
Classifier: Topic :: Software Development :: Libraries :: Python Modules
Classifier: Topic :: Utilities
Classifier: Topic :: Software Development :: Assemblers
Classifier: Topic :: Software Development
Classifier: Topic :: Software Development :: Build Tools
Classifier: Topic :: Software Development :: Code Generators
Classifier: Topic :: System :: Distributed Computing
Classifier: License :: OSI Approved :: Apache Software License
Classifier: Programming Language :: Python :: 3 :: Only
Classifier: Programming Language :: Python :: 3.9
Classifier: Programming Language :: Python :: 3.10
Classifier: Programming Language :: Python :: 3.11
Classifier: Programming Language :: Python :: 3.12
Classifier: Programming Language :: Python :: 3.13
Classifier: Operating System :: MacOS
Classifier: Operating System :: Microsoft :: Windows
Classifier: Operating System :: POSIX :: Linux
Requires-Python: >=3.9
License-File: LICENSE
Requires-Dist: requests>=2.32.3
Requires-Dist: python-dotenv>=1.0.0
Requires-Dist: qiskit>=2.0.0
Requires-Dist: qiskit-ibm-runtime>=0.38.0
Requires-Dist: pillow>=11.2.1
Dynamic: author
Dynamic: home-page
Dynamic: license-file
Dynamic: requires-python
